{"numeroProcesso":"308343/2015-8","dataInicioVigencia":"01/03/2016","dataTerminoVigencia":"28/02/2021","modalidade":{"codigo":"PQ","nome":"Produtividade em Pesquisa"},"areaConhecimento":{"codigo":"50503022","grandeArea":"Ciências Agrárias","area":"Medicina Veterinária","subarea":"Patologia Animal","especialidade":"Anatomia Patologia Animal"},"chamada":{"sigla":"PQ 2015","nome":"Produtividade em Pesquisa - PQ 2015","siglaParent":null,"nomeParent":null},"projeto":{"titulo":"Caracterização patológica  de algumas doenças que afetam suínos da creche até terminação.","objetivo":null,"resumo":"Vide projeto anexo"},"emailContato":"davetpat@ufrgs.br","identificadoresPessoa":[{"tipo":"IDLATTES","identificador":"6841118121493906"},{"tipo":"RESEARCHERID","identificador":"H-3461-2012"},{"tipo":"SCOPUSID","identificador":"35608605300"},{"tipo":"ORCID","identificador":"0000-0003-3766-0654"}],"instituicoes":[{"codigo":"019200000005","tipo":"Origem","sigla":"UFRGS","nome":"Universidade Federal do Rio Grande do Sul","siglaMacro":null,"nomeMacro":null},{"codigo":"019200000005","tipo":"Destino","sigla":"UFRGS","nome":"Universidade Federal do Rio Grande do Sul","siglaMacro":null,"nomeMacro":null},{"codigo":"019200000005","tipo":"Executora/Sede","sigla":"UFRGS","nome":"Universidade Federal do Rio Grande do Sul","siglaMacro":null,"nomeMacro":null}],"palavrasChave":"Doenças de suínos, respiratórias, entéricas, levantamento de abatedouro, ","valoresRecebidos":[{"elementoOrcamentario":{"codigo":"00","nome":"BOLSAS"},"moeda":{"codigo":"026","codigoIso":"BRL","nome":"REAL"},"valor":168000}]}