{"numeroProcesso":"305525/2016-6","dataInicioVigencia":"01/03/2017","dataTerminoVigencia":"28/02/2022","modalidade":{"codigo":"PQ","nome":"Produtividade em Pesquisa"},"areaConhecimento":{"codigo":"70402000","grandeArea":"Ciências Humanas","area":"Arqueologia","subarea":"Arqueologia Pré-Histórica","especialidade":null},"chamada":{"sigla":"PQ 2016","nome":"Chamada CNPq N º 12/2016 - Bolsas de Produtividade em Pesquisa - PQ","siglaParent":null,"nomeParent":null},"projeto":{"titulo":"Projeto de Pesquisa em Arqueologia Pré-Histórica  ","objetivo":null,"resumo":"Vide projeto anexo"},"emailContato":"aprous80@gmail.com","identificadoresPessoa":[{"tipo":"IDLATTES","identificador":"2546876510627706"}],"instituicoes":[{"codigo":"033300000002","tipo":"Origem","sigla":"UFMG","nome":"Universidade Federal de Minas Gerais","siglaMacro":null,"nomeMacro":null},{"codigo":"033300000002","tipo":"Destino","sigla":"UFMG","nome":"Universidade Federal de Minas Gerais","siglaMacro":null,"nomeMacro":null},{"codigo":"033300000002","tipo":"Executora/Sede","sigla":"UFMG","nome":"Universidade Federal de Minas Gerais","siglaMacro":null,"nomeMacro":null}],"palavrasChave":"arqueologia pré-histórica, sítios arqueológicos, arqueologia","valoresRecebidos":[]}