{"numeroProcesso":"304643/2017-3","dataInicioVigencia":"01/03/2018","dataTerminoVigencia":"28/02/2023","modalidade":{"codigo":"PQ","nome":"Produtividade em Pesquisa"},"areaConhecimento":{"codigo":"10603018","grandeArea":"Ciências Exatas e da Terra","area":"Química","subarea":"Físico-Química","especialidade":"Cinética Química e Catálise"},"chamada":{"sigla":"PQ - 2017","nome":"Chamada CNPq N º 12/2017 - Bolsas de Produtividade em Pesquisa - PQ","siglaParent":null,"nomeParent":null},"projeto":{"titulo":"Catálise sustentável para valorização de substratos bio-renováveis derivados de óleos essenciais","objetivo":null,"resumo":"Vide projeto anexo"},"emailContato":"elena@ufmg.br","identificadoresPessoa":[{"tipo":"IDLATTES","identificador":"2328030824765516"},{"tipo":"RESEARCHERID","identificador":"AAK-7600-2020"},{"tipo":"ORCID","identificador":"0000-0002-4894-8402"}],"instituicoes":[{"codigo":"033300000002","tipo":"Origem","sigla":"UFMG","nome":"Universidade Federal de Minas Gerais","siglaMacro":null,"nomeMacro":null},{"codigo":"033300000002","tipo":"Destino","sigla":"UFMG","nome":"Universidade Federal de Minas Gerais","siglaMacro":null,"nomeMacro":null},{"codigo":"033300000002","tipo":"Executora/Sede","sigla":"UFMG","nome":"Universidade Federal de Minas Gerais","siglaMacro":null,"nomeMacro":null}],"palavrasChave":"Terpenos, Química Fina, Óleos essenciais, Catálise, Substratos bio-renováveis","valoresRecebidos":[{"elementoOrcamentario":{"codigo":"00","nome":"BOLSAS"},"moeda":{"codigo":"026","codigoIso":"BRL","nome":"REAL"},"valor":100800}]}