{"numeroProcesso":"311092/2017-9","dataInicioVigencia":"01/03/2018","dataTerminoVigencia":"28/02/2023","modalidade":{"codigo":"PQ","nome":"Produtividade em Pesquisa"},"areaConhecimento":{"codigo":"10301038","grandeArea":"Ciências Exatas e da Terra","area":"Ciência da Computação","subarea":"Teoria da Computação","especialidade":"Análise de Algoritmos e Complexidade de Computação"},"chamada":{"sigla":"PQ - 2017","nome":"Chamada CNPq N º 12/2017 - Bolsas de Produtividade em Pesquisa - PQ","siglaParent":null,"nomeParent":null},"projeto":{"titulo":"Otimização e Automação de Sistemas: Modelos Algoritmos e Aplicações","objetivo":null,"resumo":"Vide projeto anexo"},"emailContato":"mateus@dcc.ufmg.br","identificadoresPessoa":[{"tipo":"IDLATTES","identificador":"6289602045034353"},{"tipo":"SCOPUSID","identificador":"6701317816"},{"tipo":"ORCID","identificador":"0000-0002-7238-0714"}],"instituicoes":[{"codigo":"033383004000","tipo":"Origem","sigla":"UFMG","nome":"Departamento de Ciência da Computação","siglaMacro":"UFMG","nomeMacro":"Universidade Federal de Minas Gerais"},{"codigo":"033383004000","tipo":"Destino","sigla":"UFMG","nome":"Departamento de Ciência da Computação","siglaMacro":"UFMG","nomeMacro":"Universidade Federal de Minas Gerais"},{"codigo":"033383004000","tipo":"Executora/Sede","sigla":"UFMG","nome":"Departamento de Ciência da Computação","siglaMacro":"UFMG","nomeMacro":"Universidade Federal de Minas Gerais"}],"palavrasChave":"Aplicações, Heurísticas, Otimização Combinatória, Algoritmos, Programação Matematica","valoresRecebidos":[{"elementoOrcamentario":{"codigo":"00","nome":"BOLSAS"},"moeda":{"codigo":"026","codigoIso":"BRL","nome":"REAL"},"valor":100800}]}