{"numeroProcesso":"310312/2018-3","dataInicioVigencia":"01/03/2019","dataTerminoVigencia":"29/02/2024","modalidade":{"codigo":"PQ","nome":"Produtividade em Pesquisa"},"areaConhecimento":{"codigo":"70804001","grandeArea":"Ciências Humanas","area":"Educação","subarea":"Ensino-Aprendizagem","especialidade":null},"chamada":{"sigla":"PQ - 2018","nome":"Chamada CNPq Nº 09/2018 - Bolsas de Produtividade em Pesquisa - PQ","siglaParent":null,"nomeParent":null},"projeto":{"titulo":"A produção acadêmica em Educação em Ciências e os saberes e práticas docentes em diferentes níveis e","objetivo":null,"resumo":"Vide projeto anexo"},"emailContato":"r.nardi@unesp.br","identificadoresPessoa":[{"tipo":"IDLATTES","identificador":"4449947783474945"},{"tipo":"RESEARCHERID","identificador":"O-2005-2013"},{"tipo":"SCOPUSID","identificador":"24367023400"},{"tipo":"ORCID","identificador":"0000-0002-5018-3621"}],"instituicoes":[{"codigo":"033000000007","tipo":"Origem","sigla":"UNESP","nome":"Universidade Estadual Paulista Júlio de Mesquita Filho","siglaMacro":null,"nomeMacro":null},{"codigo":"033000000007","tipo":"Destino","sigla":"UNESP","nome":"Universidade Estadual Paulista Júlio de Mesquita Filho","siglaMacro":null,"nomeMacro":null},{"codigo":"033000000007","tipo":"Executora/Sede","sigla":"UNESP","nome":"Universidade Estadual Paulista Júlio de Mesquita Filho","siglaMacro":null,"nomeMacro":null}],"palavrasChave":"Educação em Ciências; Ensino de Física, Formação de professores de Física, Atividades Experimentais","valoresRecebidos":[{"elementoOrcamentario":{"codigo":"00","nome":"BOLSAS"},"moeda":{"codigo":"026","codigoIso":"BRL","nome":"REAL"},"valor":67200}]}