{"numeroProcesso":"300962/2018-5","dataInicioVigencia":"01/03/2019","dataTerminoVigencia":"29/02/2024","modalidade":{"codigo":"PQ","nome":"Produtividade em Pesquisa"},"areaConhecimento":{"codigo":"10804005","grandeArea":"Ciências Exatas e da Terra","area":"Oceanografia","subarea":"Oceanografia Geológica","especialidade":null},"chamada":{"sigla":"PQ - 2018","nome":"Chamada CNPq Nº 09/2018 - Bolsas de Produtividade em Pesquisa - PQ","siglaParent":null,"nomeParent":null},"projeto":{"titulo":"Feições anômalas de fundo no talude superior do Sul do Brasil","objetivo":null,"resumo":"Vide projeto anexo"},"emailContato":"mahiques@usp.br","identificadoresPessoa":[{"tipo":"IDLATTES","identificador":"5969636750048659"},{"tipo":"RESEARCHERID","identificador":"D-1526-2010"},{"tipo":"ORCID","identificador":"0000-0002-5249-5610"}],"instituicoes":[{"codigo":"006717002003","tipo":"Origem","sigla":"USP","nome":"Departamento de Oceanografia Física","siglaMacro":"USP","nomeMacro":"Universidade de São Paulo"},{"codigo":"006717002003","tipo":"Destino","sigla":"USP","nome":"Departamento de Oceanografia Física","siglaMacro":"USP","nomeMacro":"Universidade de São Paulo"},{"codigo":"006717002003","tipo":"Executora/Sede","sigla":"USP","nome":"Departamento de Oceanografia Física","siglaMacro":"USP","nomeMacro":"Universidade de São Paulo"}],"palavrasChave":"margem continental, morfologia, sedimentação","valoresRecebidos":[{"elementoOrcamentario":{"codigo":"00","nome":"BOLSAS"},"moeda":{"codigo":"026","codigoIso":"BRL","nome":"REAL"},"valor":67200}]}