{"numeroProcesso":"304149/2019-5","dataInicioVigencia":"01/03/2020","dataTerminoVigencia":"28/02/2025","modalidade":{"codigo":"PQ","nome":"Produtividade em Pesquisa"},"areaConhecimento":{"codigo":"30405033","grandeArea":"Engenharias","area":"Engenharia Elétrica","subarea":"Eletrônica Industrial, Sistemas e Controles Eletrônicos","especialidade":"Controle de Processos Eletrônicos, Retroalimentação"},"chamada":{"sigla":"PQ - 2019","nome":"Chamada CNPq 06/2019 - Bolsas de Produtividade em Pesquisa","siglaParent":null,"nomeParent":null},"projeto":{"titulo":"Controle de Sistemas com Dinâmica Sujeita a Variações Estocásticas","objetivo":null,"resumo":"Vide projeto anexo"},"emailContato":"oswaldo@lac.usp.br","identificadoresPessoa":[{"tipo":"IDLATTES","identificador":"6829166075411185"},{"tipo":"RESEARCHERID","identificador":"G-3181-2010"},{"tipo":"ORCID","identificador":"0000-0002-0875-8698"}],"instituicoes":[{"codigo":"006716016000","tipo":"Origem","sigla":"USP","nome":"Departamento de Telecomunicações e Controle","siglaMacro":"USP","nomeMacro":"Universidade de São Paulo"},{"codigo":"006716016000","tipo":"Destino","sigla":"USP","nome":"Departamento de Telecomunicações e Controle","siglaMacro":"USP","nomeMacro":"Universidade de São Paulo"},{"codigo":"006716016000","tipo":"Executora/Sede","sigla":"USP","nome":"Departamento de Telecomunicações e Controle","siglaMacro":"USP","nomeMacro":"Universidade de São Paulo"}],"palavrasChave":"controle estocástico, controle ótimo, otimização, cadeias de Markov, processos estocásticos, filtragem","valoresRecebidos":[{"elementoOrcamentario":{"codigo":"00","nome":"BOLSAS"},"moeda":{"codigo":"026","codigoIso":"BRL","nome":"REAL"},"valor":33600}]}