{"numeroProcesso":"400127/2012-1","dataInicioVigencia":"22/03/2012","dataTerminoVigencia":"31/03/2017","modalidade":{"codigo":"APQ","nome":"Auxílio a Pesquisa"},"areaConhecimento":{"codigo":"10507167","grandeArea":"Ciências Exatas e da Terra","area":"Física","subarea":"Física da Matéria Condensada","especialidade":"Prop. Óticas e Espectrosc. da Mat. Condens; Outras Inter. da Mat. com Rad. e Part."},"chamada":{"sigla":"Enc - INCT CsF","nome":"Encomenda - Programa INCT Ciência sem Fronteiras","siglaParent":null,"nomeParent":null},"projeto":{"titulo":"INCT de Nanomateriais de Carbono","objetivo":null,"resumo":"Os nanomateriais de carbono têm sido protótipos para o desenvolvimento da nanociência e nanotecnologia desde seus primórdios, devido à riqueza de suas variadas propriedades estruturais e eletrônicas. Desde a década de 1980, uma fração considerável da pesquisa em nanociência esteve associada a estes nanomateriais: o fullereno, descoberto em 1985; os nanotubos, em 1991; o grafeno, em 2004; e as nanofitas de grafeno, em 2008. Nossa equipe é a pioneira e líder no Brasil no estudo nanomateriais de carbono, trabalhando na síntese, purificação e funcionalização, nos estudos de propriedades fundamentais, modelos teóricos e simulações computacionais, na pesquisa em dispositivos e aplicações, tais como, nanocompósitos, sensores de gases, dispositivos foto-voltáicos, células combustíveis, e transistores de efeito de campo. Temos também membros da equipe trabalhando no campo da toxicologia de nanotubos de carbono e fullerenos, na sua aplicação em metrologia, e temos duas empresas associadas à nossa proposta: a Nacional de Grafite (com interesse na produção de amostras de grafeno, de eletrodos para a produção de nanotubos e de grafite expandido) . "},"emailContato":"mpimenta@fisica.ufmg.br","identificadoresPessoa":[{"tipo":"IDLATTES","identificador":"9670001528699130"},{"tipo":"ORCID","identificador":"0000-0002-3389-0682"}],"instituicoes":[{"codigo":"033300000002","tipo":"Origem","sigla":"UFMG","nome":"Universidade Federal de Minas Gerais","siglaMacro":null,"nomeMacro":null},{"codigo":"033300000002","tipo":"Destino","sigla":"UFMG","nome":"Universidade Federal de Minas Gerais","siglaMacro":null,"nomeMacro":null},{"codigo":"033300000002","tipo":"Executora/Sede","sigla":"UFMG","nome":"Universidade Federal de Minas Gerais","siglaMacro":null,"nomeMacro":null}],"palavrasChave":"INCT","valoresRecebidos":[{"elementoOrcamentario":{"codigo":"00","nome":"BOLSAS"},"moeda":{"codigo":"001","codigoIso":"USD","nome":"DOLAR AMERICANO"},"valor":319940.66},{"elementoOrcamentario":{"codigo":"00","nome":"BOLSAS"},"moeda":{"codigo":"023","codigoIso":"EUR","nome":"UNIDADE MONET.EUROPEIA"},"valor":190968.27},{"elementoOrcamentario":{"codigo":"00","nome":"BOLSAS"},"moeda":{"codigo":"004","codigoIso":"GBP","nome":"LIBRA ESTERLINA"},"valor":119799.29},{"elementoOrcamentario":{"codigo":"00","nome":"BOLSAS"},"moeda":{"codigo":"019","codigoIso":"AUD","nome":"DOLAR AUSTRALIANO"},"valor":69824.59}]}